mitalex_project/__init__.py
mitalex_project-0.1.0.dist-info/METADATA
mitalex_project-0.1.0.dist-info/WHEEL
mitalex_project-0.1.0.dist-info/RECORD
