Metadata-Version: 2.3
Name: mitalex_project
Version: 0.1.0
Summary: My first Python package
License: MIT
Author: Митрофаов Александр
Author-email: mitrofan7879@gmail.com
Requires-Python: >=3.12
Classifier: License :: OSI Approved :: MIT License
Classifier: Programming Language :: Python :: 3
Classifier: Programming Language :: Python :: 3.12
Classifier: Programming Language :: Python :: 3.13
